{
  "title": {
    "FQL"   	:   "发气量\nL\\(Kg)",
    "CLSJ"  	:   "出炉时间\n(hh:mm)",
    "CLSL"  	:   "出炉数量\n(炉)",
    "BYQDWBa"	: 	"变压器档位\nBa",
	"BYQDWBb"	:	"变压器档位\nBb",
	"BYQDWBc"	:	"变压器档位\nBc",
	"BYQWDAX"	:	"变压器温度\nA相\n(°C)",
	"BYQWDBX"	:	"变压器温度\nB相\n(°C)",
	"BYQWDCX"	:	"变压器温度\nC相\n(°C)",
	"CJDYVa"	:	"次级电压\nVa\n(V)",
	"CJDYVb"	:	"次级电压\nVb\n(V)",
	"CJDYVc"	:	"次级电压\nVc\n(V)",
	"CZDLIa"	:	"操作电流\nIa\n(kA)",
	"CZDLIb"	:	"操作电流\nIb\n(kA)",
	"CZDLIc"	:	"操作电流\nIc\n(kA)",
	"CZDZRa"	:	"操作电阻\nRa\n(mΩ)",
	"CZDZRb"	:	"操作电阻\nRb\n(mΩ)",
	"CZDZRc"	:	"操作电阻\nRc\n(mΩ)",
	"DJDYVa"	:	"电极电压\nVa\n(V)",
	"DJDYVb"	:	"电极电压\nVb\n(V)",
	"DJDYVc"	:	"电极电压\nVc\n(V)",
	"DJWZ1"		:	"电极位置\n1#\n(mm)",
	"DJWZ2"		:	"电极位置\n2#\n(mm)",
	"DJWZ3"		:	"电极位置\n3#\n(mm)",
	"DL"		:	"电力\n(kWh)",
	"GLYS"		:	"功率因数",
	"LDWD1"		:	"炉底温度1\n(°C)",
	"LDWD2"		:	"炉底温度2\n(°C)",
	"LDWD3"		:	"炉底温度3\n(°C)",
	"LDWD4"		:	"炉底温度4\n(°C)",
	"LDWD5"		:	"炉底温度5\n(°C)",
	"LDWD6"		:	"炉底温度6\n(°C)",
	"LDWD7"		:	"炉底温度7\n(°C)",
	"LQWD"		:	"炉气温度\n(°C)",
	"LYH"		:	"炉眼号\n(#)",
	"WGGL"		:	"无功功率\n(MVar)",
	"XHSCSWD"	:	"循环水\n回水温度\n(°C)",
	"XHSJSWD"	:	"循环水\n进水温度\n(°C)",
	"YCDLIa"	:	"一次电流\nIa\n(A)",
	"YCDLIb"	:	"一次电流\nIb\n(A)",
	"YCDLIc"	:	"一次电流\nIc\n(A)",
	"YCDYVa"	:	"一次电压\nVa\n(kV)",
	"YCDYVb"	:	"一次电压\nVb\n(kV)",
	"YCDYVc"	:	"一次电压\nVc\n(kV)",
	"YGGL"		:	"有功功率\n(MW)"
  }
}